admin_export/__init__.py
admin_export/admin.py
django_simple_admin_export-0.0.1.dist-info/DESCRIPTION.rst
django_simple_admin_export-0.0.1.dist-info/METADATA
django_simple_admin_export-0.0.1.dist-info/metadata.json
django_simple_admin_export-0.0.1.dist-info/RECORD
django_simple_admin_export-0.0.1.dist-info/top_level.txt
django_simple_admin_export-0.0.1.dist-info/WHEEL
