Metadata-Version: 2.0
Name: django-simple-admin-export
Version: 0.0.1
Summary: UNKNOWN
Home-page: https://bitbucket.org/albertoconnor/django-simple-admin-export
Author: Albert O'Connor
Author-email: info@albertoconnor.ca
License: UNKNOWN
Platform: UNKNOWN
Classifier: Development Status :: 4 - Beta
Classifier: Framework :: Django
Classifier: Programming Language :: Python :: 2.7
Classifier: License :: OSI Approved :: MIT License
Classifier: Operating System :: OS Independent
Classifier: Topic :: Software Development
Requires-Dist: unicodecsv (==0.9.4)
